LICENSE
README.md
setup.py
pushoverwrap/__init__.py
pushoverwrap/pushover.py
pushoverwrap.egg-info/PKG-INFO
pushoverwrap.egg-info/SOURCES.txt
pushoverwrap.egg-info/dependency_links.txt
pushoverwrap.egg-info/top_level.txt