Metadata-Version: 2.1
Name: pushoverwrap
Version: 0.1.0
Summary: A simple Pushover API wrapper.
Home-page: https://github.com/plutotree/pushovewrap
Author: plutotree
Author-email: plutotreetree@gmail.com
License: MIT
Classifier: Programming Language :: Python :: 3
Classifier: License :: OSI Approved :: MIT License
Requires-Python: >=3.6
License-File: LICENSE
